<?xml version="1.0" encoding="utf-8"?>
<odoo>

    <record id="l10n_latam_document_pool_form" model="ir.ui.view">
        <field name="name">l10n_latam.document.pool.form</field>
        <field name="model">l10n_latam.document.pool</field>
        <field name="arch" type="xml">
            <form>
                <header>
                    <button name="action_confirm" string="Confirm" type="object" class="oe_highlight"
                            attrs="{'invisible':[('state','!=','draft')]}" />
                    <button name="action_queue" string="Queue" type="object"
                            attrs="{'invisible':['|', ('state','!=','draft'), ('can_be_queued', '=', False)]}" />
                    <button name="action_cancel" string="Cancel" type="object"
                            attrs="{'invisible':[('state','in', ('cancelled', 'draft'))]}" />
                    <field name="state" widget="statusbar" statusbar_visible="active,depleted" />
                </header>
                <sheet>
                    <field name="can_be_queued" invisible="1" />
                    <div class="oe_button_box" name="button_box">
                        <button class="oe_stat_button" name="action_view_sequence" icon="fa-arrow-right" type="object" groups="base.group_system" attrs="{'invisible': [('sequence_id', '=', False)] }">
                            <span class="o_stat_text">Sequence</span>
                        </button>
                    </div>
                    <group>
                        <div class="oe_title">
                            <h2>
                                <field name="name" placeholder="Eg : 8001695033" />
                            </h2>
                        </div>
                    </group>
                    <group>
                        <group>
                            <field name="l10n_latam_document_type_id" widget="selection"/>
                            <field name="sequence_start" />
                            <field name="sequence_end" />
                            <field name="expiration_date" />
                        </group>
                        <group>
                            <field name="warning_gap" invisible="1" />
                            <label string="Remaining warning" for="remaining_percentage" />
                            <div class="o_row" name="remaining_percentage">
                                <field name="remaining_percentage" />
                                <span>%</span>
                            </div>
                            <field name="number_next_actual" invisible="1" />
                            <field name="sequence_remaining" attrs="{'invisible': [('state', 'in', ('draft', 'cancelled'))]}" />
                            <field name="next_fiscal_number" attrs="{'invisible': [('state', 'in', ('draft', 'cancelled'))]}" />
                            <field name="sequence_id" invisible="1" />
                            <field name="company_id" groups="base.group_multi_company" />
                        </group>
                    </group>
                </sheet>
                <div class="oe_chatter">
                    <field name="message_follower_ids" widget="mail_followers" groups="base.group_user" />
                    <field name="message_ids" widget="mail_thread" />
                </div>
            </form>
        </field>
    </record>

    <record id="l10n_latam_document_pool_tree" model="ir.ui.view">
        <field name="name">l10n_latam.document.pool.tree</field>
        <field name="model">l10n_latam.document.pool</field>
        <field name="arch" type="xml">
            <tree>
                <field name="name" />
                <field name="l10n_latam_document_type_id" />
                <field name="next_fiscal_number" />
                <field name="sequence_start" />
                <field name="sequence_end" />
                <field name="state" />
                <field name="company_id" groups="base.group_multi_company" />
            </tree>
        </field>
    </record>

    <record id="l10n_latam_document_pool_search" model="ir.ui.view">
        <field name="name">l10n_latam.document.pool.search</field>
        <field name="model">l10n_latam.document.pool</field>
        <field name="arch" type="xml">
            <search>
                <field name="name" />
                <field name="l10n_latam_document_type_id" />
                <filter name="draft" string="Draft" domain="[('state','=','draft')]" />
                <filter name="active" string="Active" domain="[('state','in',('active', 'draft'))]" />
                <filter name="queue" string="Queue" domain="[('state','=','queue')]" />
                <filter name="depleted" string="Depleted" domain="[('state','=','depleted')]" />
                <filter name="expired" string="Expired" domain="[('state','=','expired')]" />
                <filter name="cancelled" string="Cancelled" domain="[('state','=','cancelled')]" />
                <separator />
                <filter name="sale" string="Sale" domain="[('type','=','sale')]" />
                <filter name="purchase" string="Purchase" domain="[('type','=','purchase')]" />
                <filter name="credit_note" string="Credit Note" domain="[('type','=','credit_note')]" />
                <filter name="debit_note" string="Debit Note" domain="[('type','=','debit_note')]" />
                <group expand="0" string="Group By">
                    <filter name="type" string="Type" domain="[]" context="{'group_by':'l10n_latam_document_type_id'}" />
                    <filter name="state" string="State" domain="[]" context="{'group_by':'state'}" />
                    <filter name="company_id" string="Company" domain="[]" context="{'group_by':'company_id'}" groups="base.group_multi_company" />
                </group>
            </search>
        </field>
    </record>

    <record id="action_document_pool" model="ir.actions.act_window">
        <field name="name">Document Pools</field>
        <field name="type">ir.actions.act_window</field>
        <field name="res_model">l10n_latam.document.pool</field>
        <field name="search_view_id" ref="l10n_latam_document_pool_search" />
        <field name="context">{'search_default_active': 1}</field>
        <field name="help" type="html">
            <p class="o_view_nocontent_empty_folder">
                No Document Pools found!
            </p>
            <p>
                You can create your first Document Pool here.
            </p>
        </field>
    </record>

    <!-- <record model="ir.actions.act_window" id="action_document_pool">
        <field name="name">Document Pools</field>
        <field name="res_model">l10n_latam.document.pool</field>
        <field name="domain">['|', ('active', '=', True), ('active', '=', False)]</field>
        <field name="context">{"search_default_active":1}</field>
    </record> -->

    <menuitem action="action_document_pool" id="menu_document_type" sequence="21" parent="account.account_account_menu"/> />

</odoo>
