<?xml version="1.0" encoding="UTF-8"?>
<templates id="template">

    <t t-extend="ClientDetailsEdit">
        <t t-jquery=".client-details-left" t-operation="append">

            <div class='client-detail'>
                <span class='label'>NCF</span>
                <select class='detail client-fiscal-type needsclick' name='sale_fiscal_type'>
                    <option value=''>None</option>
                    <t t-foreach='widget.pos.sale_fiscal_type_selection' t-as='row'>
                        <option t-att-value='row[0]'
                                t-att-selected="partner.sale_fiscal_type ? ((row[0] === partner.sale_fiscal_type) ? true : undefined) : undefined">
                            <t t-esc='row[1]'/>
                        </option>
                    </t>
                </select>
            </div>

        </t>
    </t>

    <t t-extend="ClientDetails">
        <t t-jquery=".client-details-left" t-operation="append">
            <div class='client-detail'>
                <span class='label'>NCF</span>
                <t t-if='partner.sale_fiscal_type'>
                    <span class='detail client-sale-fiscal-type'>
                        <t t-foreach='widget.pos.sale_fiscal_type_selection' t-as='row'>
                            <t t-if='row[0] === partner.sale_fiscal_type'>
                                <t t-esc="row[1]"/>
                            </t>
                        </t>
                    </span>
                </t>
                <t t-if='!partner.sale_fiscal_type'>
                    <span class='detail client-sale_fiscal_type empty'>N/A</span>
                </t>
            </div>
        </t>
    </t>

    <t t-extend="ActionpadWidget">
        <t t-jquery=".fa.fa-user" t-operation="replace">
            <i class='fa fa-user'/>
            <t t-set="partner" t-value="widget.pos.get_client()"/>

            <t t-if='partner'>
                <t t-if='partner.sale_fiscal_type'>
                    <t t-foreach='widget.pos.sale_fiscal_type_selection' t-as='row'>
                        <t t-if='row[0] === partner.sale_fiscal_type'>
                            <span style="color:red">
                                <t t-esc="row[1]"/>
                            </span>
                        </t>
                    </t>
                </t>
            </t>
        </t>
    </t>

    <t t-extend="ClientListScreenWidget">
        <t t-jquery="table.client-list>thead>tr" t-operation="replace">
            <th>Tax ID</th>
            <th>Name</th>
            <th>Phone</th>
        </t>
    </t>

    <t t-extend="ClientLine">
        <t t-jquery=".client-line" t-operation="replace">
            <tr class='client-line' t-att-data-id='partner.id'>
                <td>
                    <t t-if="partner.vat">
                        <t t-esc='partner.vat'/>
                    </t>
                </td>
                <td>
                    <t t-esc='partner.name'/>
                </td>
                <td>
                    <t t-esc='partner.phone or partner.mobile or ""'/>
                </td>
            </tr>
        </t>
    </t>

    <t t-name="QueryInvoicesButton">
        <span class='control-button'>
            <!--<i class='fa fa-search' />-->
            All Invoices
        </span>
    </t>

    <t t-name="InvoicesListScreenWidget">
        <div class="clientlist-screen screen">
            <div class="screen-content">
                <section class="top-content">
                    <span class='button back'>
                        <i class='fa fa-angle-double-left'></i>
                        Cancel
                    </span>
                    <span class='searchbox'>
                        <input class="invoices_search" placeholder='Search Invoices'/>
                        <span class='search-clear'></span>
                    </span>
                    <span class='button search'>
                        Search
                    </span>
                </section>
                <section class="full-content">
                    <div class='window'>
                        <section class='subwindow collapsed'>
                            <div class='subwindow-container collapsed'>
                                <div class='subwindow-container-fix client-details-contents'>
                                </div>
                            </div>
                        </section>
                        <section class='subwindow'>
                            <div class='subwindow-container'>
                                <div class='subwindow-container-fix touch-scrollable scrollable-y'>
                                    <table class='client-list'>
                                        <thead>
                                            <tr>
                                                <th>Fecha Orden</th>
                                                <th>Tax ID</th>
                                                <th>Cliente</th>
                                                <th>Monto</th>
                                                <th>Estado</th>
                                            </tr>
                                        </thead>
                                        <tbody class='client-list-contents'>
                                        </tbody>
                                    </table>
                                </div>
                            </div>
                        </section>
                    </div>
                </section>
            </div>
        </div>

        <!--<div class="clientlist-screen screen">-->
        <!--<div class="screen-content">-->
        <!--<section class="top-content">-->
        <!--<span class='button back'>-->
        <!--<i class='fa fa-angle-double-left'></i>-->
        <!--Back-->
        <!--</span>-->
        <!--<span class='searchbox'>-->
        <!--<input placeholder='Search Invoices' />-->
        <!--<span class='search-clear'></span>-->
        <!--</span>-->
        <!--<span class='searchbox'></span>-->
        <!--<span class='button search'>-->
        <!--Search-->
        <!--</span>-->
        <!--</section>-->
        <!--<section class="full-content">-->
        <!--<div class='window'>-->
        <!--<section class='subwindow collapsed'>-->
        <!--<div class='subwindow-container collapsed'>-->
        <!--<div class='subwindow-container-fix client-details-contents'>-->
        <!--</div>-->
        <!--</div>-->
        <!--</section>-->
        <!--<section class='subwindow'>-->
        <!--<div class='subwindow-container'>-->
        <!--<div class='subwindow-container-fix touch-scrollable scrollable-y'>-->
        <!--<table class='client-list'>-->
        <!--<thead>-->
        <!--<tr>-->
        <!--<th>Fecha Orden</th>-->
        <!--<th>Tax ID</th>-->
        <!--<th>Cliente</th>-->
        <!--<th>Monto</th>-->
        <!--<th>Estado</th>-->
        <!--</tr>-->
        <!--</thead>-->
        <!--<tbody class='client-list-contents'>-->
        <!--</tbody>-->
        <!--</table>-->
        <!--</div>-->
        <!--</div>-->
        <!--</section>-->
        <!--</div>-->
        <!--</section>-->
        <!--</div>-->
        <!--</div>-->
    </t>

</templates>
